bluer_amr/README.py
bluer_amr/__init__.py
bluer_amr/__main__.py
bluer_amr/config.env
bluer_amr/env.py
bluer_amr/functions.py
bluer_amr/host.py
bluer_amr/logger.py
bluer_amr/urls.py
bluer_amr/.abcli/abcli.sh
bluer_amr/.abcli/actions.sh
bluer_amr/.abcli/alias.sh
bluer_amr/.abcli/bluer_AMR.sh
bluer_amr/.abcli/tests/README.sh
bluer_amr/.abcli/tests/help.sh
bluer_amr/.abcli/tests/version.sh
bluer_amr/help/__init__.py
bluer_amr/help/__main__.py
bluer_amr/help/functions.py
bluer_amr-6.11.1.dist-info/licenses/LICENSE
bluer_amr-6.11.1.dist-info/METADATA
bluer_amr-6.11.1.dist-info/WHEEL
bluer_amr-6.11.1.dist-info/top_level.txt
bluer_amr-6.11.1.dist-info/RECORD
