Metadata-Version: 2.4
Name: bluer_amr
Version: 6.11.1
Summary: 🔬 meta-analysis of clinical outcomes of antibiotics for cholera treatment and percentage of antibiotic resistance.
Home-page: https://github.com/kamangir/bluer-amr
Author: Arash Abadpour (Kamangir)
Author-email: arash.abadpour@gmail.com
License: CC0-1.0
Classifier: Programming Language :: Python :: 3
Classifier: Programming Language :: Unix Shell
Classifier: Operating System :: OS Independent
License-File: LICENSE
Requires-Dist: bluer_ai
Requires-Dist: openpyxl
Dynamic: author
Dynamic: author-email
Dynamic: classifier
Dynamic: description
Dynamic: description-content-type
Dynamic: home-page
Dynamic: license
Dynamic: license-file
Dynamic: requires-dist
Dynamic: summary
